Workbook

Sheet README
A1: Operating Budget Model (2026) – Live Excel / Google Sheets Template
A3: How to use:
A4: 1) Go to Inputs: set Scenario, Start Cash, Additional Funding, and monthly Revenue assumptions.
A5: 2) Review Challenge Payout Tiers: adjust thresholds and payout % if needed.
A6: 3) Operating_2026 updates automatically. StressTest shows Base vs Stress side-by-side.
A8: Color key:
A9: Blue text = inputs you can edit. Black text = formulas.
A11: Notes:
A12: • No dynamic array functions are used (compatible with Excel + Google Sheets).
A13: • All currency values are EUR (€). Zeros display as '-'. Negatives show in red parentheses.
A17: Reference: Liquidity planning from Manuel Liquidity-Plan Oct 2025

Sheet Inputs
A1: INPUTS (edit blue cells)
A3: Scenario & Funding
A4: Scenario (Base/Stress) | B4: Base
A5: Stress revenue multiplier | B5: 0.75
A6: Start cash (begin Jan 2026) | B6: 1000000
A7: Additional funding amount | B7: 2000000
A8: Additional funding month (1-12) | B8: 5
A10: Cost Parameters
A11: Campaign spend % (Base) | B11: 0.15
A12: Campaign spend % (Stress) | B12: 0.1
A13: Eligible payout base % of revenue | B13: 1
A14: Stress payout rate adjustment | B14: 0.9
A15: Max challenge payout % of revenue (cap) | B15: 0.45
A16: Mobile trader monthly cost | B16: 0
A17: Mobile trader start month (1-12; 13=off) | B17: 1
A18: CME dataset monthly cost | B18: 16200
A19: CME dataset start month (1-12; 13=off) | B19: 1
A20: Other fixed ops / tools (monthly) | B20: 20000
A22: Monthly Assumptions (2026)
A23: Month | B23: Revenue (Base) | C23: Team Cost | D23: Loan Repayment
A24: 46023 | B24: 25000 | C24: 85000 | D24: 58000
A25: 46054 | B25: 30000 | C25: 85000 | D25: 0
A26: 46082 | B26: 36000 | C26: 85000 | D26: 0
A27: 46113 | B27: 43000 | C27: 85000 | D27: 0
A28: 46143 | B28: 52000 | C28: 85000 | D28: 0
A29: 46174 | B29: 62000 | C29: 85000 | D29: 0
A30: 46204 | B30: 75000 | C30: 100000 | D30: 58000
A31: 46235 | B31: 90000 | C31: 100000 | D31: 0
A32: 46266 | B32: 108000 | C32: 100000 | D32: 0
A33: 46296 | B33: 130000 | C33: 100000 | D33: 0
A34: 46327 | B34: 156000 | C34: 100000 | D34: 0
A35: 46357 | B35: 187000 | C35: 100000 | D35: 0

Sheet Marketing-Budget
A2: Month | B2: Google Ads | C2: Meta Ads | D2: Tiktok Ads | E2: X Ads | F2: LinkedIn Ads | G2: Influencer-Marketing | H2: Affiliate-Cost (x% of rev) | I2: Giveaway Payouts | J2: Marketing Team | K2: Marketing Tools
A3: 46023
A4: 46054
A5: 46082
A6: 46113
A7: 46143
A8: 46174
A9: 46204
A10: 46235
A11: 46266
A12: 46296
A13: 46327
A14: 46357

Sheet Tiers
A1: Challenge Payout Tiers (sorted ascending, used with VLOOKUP TRUE)
A3: Lower bound (Payout Base €) | B3: Payout %
A4: 0 | B4: 0.3
A5: 5000 | B5: 0.4
A6: 20000 | B6: 0.5
A7: 50000 | B7: 0.6
A8: Tip: If you want payout tiers based on trader PnL instead of revenue, set Payout Base in Operating_2026 to trader PnL.

Sheet Operating_2026
A1: Operating Budget (2026)
A3: Scenario: | B3: =Inputs!$B$4 -> Base
A4: Min ending cash: | B4: =MIN($P$8:$P$19) -> 590800
A5: Ending cash (Dec): | B5: =$P$19 -> 1977200
A7: Month | B7: Begin Cash | C7: Revenue | D7: Team Cost | E7: Campaign | F7: Payout Base | G7: Payout % | H7: Challenge Payout | I7: Rev-vs-Payout ratio | J7: Loan | K7: Mobile Trader | L7: CME Dataset | M7: Total Costs | N7: Net Cashflow | O7: Funding In | P7: End Cash | Q7: Month#
A8: 46023 | B8: =Inputs!$B$6 -> 1000000 | C8: =VLOOKUP($A8,Inputs!$A$24:$B$35,2,FALSE)*IF(Inputs!$B$4="Stress",Inputs!$B$5,1) -> 25000 | D8: =VLOOKUP($A8,Inputs!$A$24:$C$35,3,FALSE) -> 85000 | E8: =C8*IF(Inputs!$B$4="Stress",Inputs!$B$12,Inputs!$B$11) -> 3750 | F8: =C8*Inputs!$B$13 -> 25000 | G8: =VLOOKUP(F8,Tiers!$A$4:$B$7,2,TRUE)*IF(Inputs!$B$4="Stress",Inputs!$B$14,1) -> 0.5 | H8: =MIN(C8*Inputs!$B$15,F8*G8) -> 11250 | I8: =H8/C8 -> 0.45 | J8: =VLOOKUP($A8,Inputs!$A$24:$D$35,4,FALSE) -> 58000 | K8: =IF($Q8>=Inputs!$B$17,Inputs!$B$16,0) -> 0 | L8: =IF($Q8>=Inputs!$B$19,Inputs!$B$18,0) -> 16200 | M8: =SUM(D8,E8,H8,J8,K8,L8) -> 174200 | N8: =C8-M8 -> -149200 | O8: =IF($Q8=Inputs!$B$8,Inputs!$B$7,0) -> 0 | P8: =B8+N8+O8 -> 850800 | Q8: 1
A9: 46054 | B9: =P8 -> 850800 | C9: =VLOOKUP($A9,Inputs!$A$24:$B$35,2,FALSE)*IF(Inputs!$B$4="Stress",Inputs!$B$5,1) -> 30000 | D9: =VLOOKUP($A9,Inputs!$A$24:$C$35,3,FALSE) -> 85000 | E9: =C9*IF(Inputs!$B$4="Stress",Inputs!$B$12,Inputs!$B$11) -> 4500 | F9: =C9*Inputs!$B$13 -> 30000 | G9: =VLOOKUP(F9,Tiers!$A$4:$B$7,2,TRUE)*IF(Inputs!$B$4="Stress",Inputs!$B$14,1) -> 0.5 | H9: =MIN(C9*Inputs!$B$15,F9*G9) -> 13500 | I9: =H9/C9 -> 0.45 | J9: =VLOOKUP($A9,Inputs!$A$24:$D$35,4,FALSE) -> 0 | K9: =IF($Q9>=Inputs!$B$17,Inputs!$B$16,0) -> 0 | L9: =IF($Q9>=Inputs!$B$19,Inputs!$B$18,0) -> 16200 | M9: =SUM(D9,E9,H9,J9,K9,L9) -> 119200 | N9: =C9-M9 -> -89200 | O9: =IF($Q9=Inputs!$B$8,Inputs!$B$7,0) -> 0 | P9: =B9+N9+O9 -> 761600 | Q9: 2
A10: 46082 | B10: =P9 -> 761600 | C10: =VLOOKUP($A10,Inputs!$A$24:$B$35,2,FALSE)*IF(Inputs!$B$4="Stress",Inputs!$B$5,1) -> 36000 | D10: =VLOOKUP($A10,Inputs!$A$24:$C$35,3,FALSE) -> 85000 | E10: =C10*IF(Inputs!$B$4="Stress",Inputs!$B$12,Inputs!$B$11) -> 5400 | F10: =C10*Inputs!$B$13 -> 36000 | G10: =VLOOKUP(F10,Tiers!$A$4:$B$7,2,TRUE)*IF(Inputs!$B$4="Stress",Inputs!$B$14,1) -> 0.5 | H10: =MIN(C10*Inputs!$B$15,F10*G10) -> 16200 | I10: =H10/C10 -> 0.45 | J10: =VLOOKUP($A10,Inputs!$A$24:$D$35,4,FALSE) -> 0 | K10: =IF($Q10>=Inputs!$B$17,Inputs!$B$16,0) -> 0 | L10: =IF($Q10>=Inputs!$B$19,Inputs!$B$18,0) -> 16200 | M10: =SUM(D10,E10,H10,J10,K10,L10) -> 122800 | N10: =C10-M10 -> -86800 | O10: =IF($Q10=Inputs!$B$8,Inputs!$B$7,0) -> 0 | P10: =B10+N10+O10 -> 674800 | Q10: 3
A11: 46113 | B11: =P10 -> 674800 | C11: =VLOOKUP($A11,Inputs!$A$24:$B$35,2,FALSE)*IF(Inputs!$B$4="Stress",Inputs!$B$5,1) -> 43000 | D11: =VLOOKUP($A11,Inputs!$A$24:$C$35,3,FALSE) -> 85000 | E11: =C11*IF(Inputs!$B$4="Stress",Inputs!$B$12,Inputs!$B$11) -> 6450 | F11: =C11*Inputs!$B$13 -> 43000 | G11: =VLOOKUP(F11,Tiers!$A$4:$B$7,2,TRUE)*IF(Inputs!$B$4="Stress",Inputs!$B$14,1) -> 0.5 | H11: =MIN(C11*Inputs!$B$15,F11*G11) -> 19350 | I11: =H11/C11 -> 0.45 | J11: =VLOOKUP($A11,Inputs!$A$24:$D$35,4,FALSE) -> 0 | K11: =IF($Q11>=Inputs!$B$17,Inputs!$B$16,0) -> 0 | L11: =IF($Q11>=Inputs!$B$19,Inputs!$B$18,0) -> 16200 | M11: =SUM(D11,E11,H11,J11,K11,L11) -> 127000 | N11: =C11-M11 -> -84000 | O11: =IF($Q11=Inputs!$B$8,Inputs!$B$7,0) -> 0 | P11: =B11+N11+O11 -> 590800 | Q11: 4
A12: 46143 | B12: =P11 -> 590800 | C12: =VLOOKUP($A12,Inputs!$A$24:$B$35,2,FALSE)*IF(Inputs!$B$4="Stress",Inputs!$B$5,1) -> 52000 | D12: =VLOOKUP($A12,Inputs!$A$24:$C$35,3,FALSE) -> 85000 | E12: =C12*IF(Inputs!$B$4="Stress",Inputs!$B$12,Inputs!$B$11) -> 7800 | F12: =C12*Inputs!$B$13 -> 52000 | G12: =VLOOKUP(F12,Tiers!$A$4:$B$7,2,TRUE)*IF(Inputs!$B$4="Stress",Inputs!$B$14,1) -> 0.6 | H12: =MIN(C12*Inputs!$B$15,F12*G12) -> 23400 | I12: =H12/C12 -> 0.45 | J12: =VLOOKUP($A12,Inputs!$A$24:$D$35,4,FALSE) -> 0 | K12: =IF($Q12>=Inputs!$B$17,Inputs!$B$16,0) -> 0 | L12: =IF($Q12>=Inputs!$B$19,Inputs!$B$18,0) -> 16200 | M12: =SUM(D12,E12,H12,J12,K12,L12) -> 132400 | N12: =C12-M12 -> -80400 | O12: =IF($Q12=Inputs!$B$8,Inputs!$B$7,0) -> 2000000 | P12: =B12+N12+O12 -> 2510400 | Q12: 5
A13: 46174 | B13: =P12 -> 2510400 | C13: =VLOOKUP($A13,Inputs!$A$24:$B$35,2,FALSE)*IF(Inputs!$B$4="Stress",Inputs!$B$5,1) -> 62000 | D13: =VLOOKUP($A13,Inputs!$A$24:$C$35,3,FALSE) -> 85000 | E13: =C13*IF(Inputs!$B$4="Stress",Inputs!$B$12,Inputs!$B$11) -> 9300 | F13: =C13*Inputs!$B$13 -> 62000 | G13: =VLOOKUP(F13,Tiers!$A$4:$B$7,2,TRUE)*IF(Inputs!$B$4="Stress",Inputs!$B$14,1) -> 0.6 | H13: =MIN(C13*Inputs!$B$15,F13*G13) -> 27900 | I13: =H13/C13 -> 0.45 | J13: =VLOOKUP($A13,Inputs!$A$24:$D$35,4,FALSE) -> 0 | K13: =IF($Q13>=Inputs!$B$17,Inputs!$B$16,0) -> 0 | L13: =IF($Q13>=Inputs!$B$19,Inputs!$B$18,0) -> 16200 | M13: =SUM(D13,E13,H13,J13,K13,L13) -> 138400 | N13: =C13-M13 -> -76400 | O13: =IF($Q13=Inputs!$B$8,Inputs!$B$7,0) -> 0 | P13: =B13+N13+O13 -> 2434000 | Q13: 6
A14: 46204 | B14: =P13 -> 2434000 | C14: =VLOOKUP($A14,Inputs!$A$24:$B$35,2,FALSE)*IF(Inputs!$B$4="Stress",Inputs!$B$5,1) -> 75000 | D14: =VLOOKUP($A14,Inputs!$A$24:$C$35,3,FALSE) -> 100000 | E14: =C14*IF(Inputs!$B$4="Stress",Inputs!$B$12,Inputs!$B$11) -> 11250 | F14: =C14*Inputs!$B$13 -> 75000 | G14: =VLOOKUP(F14,Tiers!$A$4:$B$7,2,TRUE)*IF(Inputs!$B$4="Stress",Inputs!$B$14,1) -> 0.6 | H14: =MIN(C14*Inputs!$B$15,F14*G14) -> 33750 | I14: =H14/C14 -> 0.45 | J14: =VLOOKUP($A14,Inputs!$A$24:$D$35,4,FALSE) -> 58000 | K14: =IF($Q14>=Inputs!$B$17,Inputs!$B$16,0) -> 0 | L14: =IF($Q14>=Inputs!$B$19,Inputs!$B$18,0) -> 16200 | M14: =SUM(D14,E14,H14,J14,K14,L14) -> 219200 | N14: =C14-M14 -> -144200 | O14: =IF($Q14=Inputs!$B$8,Inputs!$B$7,0) -> 0 | P14: =B14+N14+O14 -> 2289800 | Q14: 7
A15: 46235 | B15: =P14 -> 2289800 | C15: =VLOOKUP($A15,Inputs!$A$24:$B$35,2,FALSE)*IF(Inputs!$B$4="Stress",Inputs!$B$5,1) -> 90000 | D15: =VLOOKUP($A15,Inputs!$A$24:$C$35,3,FALSE) -> 100000 | E15: =C15*IF(Inputs!$B$4="Stress",Inputs!$B$12,Inputs!$B$11) -> 13500 | F15: =C15*Inputs!$B$13 -> 90000 | G15: =VLOOKUP(F15,Tiers!$A$4:$B$7,2,TRUE)*IF(Inputs!$B$4="Stress",Inputs!$B$14,1) -> 0.6 | H15: =MIN(C15*Inputs!$B$15,F15*G15) -> 40500 | I15: =H15/C15 -> 0.45 | J15: =VLOOKUP($A15,Inputs!$A$24:$D$35,4,FALSE) -> 0 | K15: =IF($Q15>=Inputs!$B$17,Inputs!$B$16,0) -> 0 | L15: =IF($Q15>=Inputs!$B$19,Inputs!$B$18,0) -> 16200 | M15: =SUM(D15,E15,H15,J15,K15,L15) -> 170200 | N15: =C15-M15 -> -80200 | O15: =IF($Q15=Inputs!$B$8,Inputs!$B$7,0) -> 0 | P15: =B15+N15+O15 -> 2209600 | Q15: 8
A16: 46266 | B16: =P15 -> 2209600 | C16: =VLOOKUP($A16,Inputs!$A$24:$B$35,2,FALSE)*IF(Inputs!$B$4="Stress",Inputs!$B$5,1) -> 108000 | D16: =VLOOKUP($A16,Inputs!$A$24:$C$35,3,FALSE) -> 100000 | E16: =C16*IF(Inputs!$B$4="Stress",Inputs!$B$12,Inputs!$B$11) -> 16200 | F16: =C16*Inputs!$B$13 -> 108000 | G16: =VLOOKUP(F16,Tiers!$A$4:$B$7,2,TRUE)*IF(Inputs!$B$4="Stress",Inputs!$B$14,1) -> 0.6 | H16: =MIN(C16*Inputs!$B$15,F16*G16) -> 48600 | I16: =H16/C16 -> 0.45 | J16: =VLOOKUP($A16,Inputs!$A$24:$D$35,4,FALSE) -> 0 | K16: =IF($Q16>=Inputs!$B$17,Inputs!$B$16,0) -> 0 | L16: =IF($Q16>=Inputs!$B$19,Inputs!$B$18,0) -> 16200 | M16: =SUM(D16,E16,H16,J16,K16,L16) -> 181000 | N16: =C16-M16 -> -73000 | O16: =IF($Q16=Inputs!$B$8,Inputs!$B$7,0) -> 0 | P16: =B16+N16+O16 -> 2136600 | Q16: 9
A17: 46296 | B17: =P16 -> 2136600 | C17: =VLOOKUP($A17,Inputs!$A$24:$B$35,2,FALSE)*IF(Inputs!$B$4="Stress",Inputs!$B$5,1) -> 130000 | D17: =VLOOKUP($A17,Inputs!$A$24:$C$35,3,FALSE) -> 100000 | E17: =C17*IF(Inputs!$B$4="Stress",Inputs!$B$12,Inputs!$B$11) -> 19500 | F17: =C17*Inputs!$B$13 -> 130000 | G17: =VLOOKUP(F17,Tiers!$A$4:$B$7,2,TRUE)*IF(Inputs!$B$4="Stress",Inputs!$B$14,1) -> 0.6 | H17: =MIN(C17*Inputs!$B$15,F17*G17) -> 58500 | I17: =H17/C17 -> 0.45 | J17: =VLOOKUP($A17,Inputs!$A$24:$D$35,4,FALSE) -> 0 | K17: =IF($Q17>=Inputs!$B$17,Inputs!$B$16,0) -> 0 | L17: =IF($Q17>=Inputs!$B$19,Inputs!$B$18,0) -> 16200 | M17: =SUM(D17,E17,H17,J17,K17,L17) -> 194200 | N17: =C17-M17 -> -64200 | O17: =IF($Q17=Inputs!$B$8,Inputs!$B$7,0) -> 0 | P17: =B17+N17+O17 -> 2072400 | Q17: 10
A18: 46327 | B18: =P17 -> 2072400 | C18: =VLOOKUP($A18,Inputs!$A$24:$B$35,2,FALSE)*IF(Inputs!$B$4="Stress",Inputs!$B$5,1) -> 156000 | D18: =VLOOKUP($A18,Inputs!$A$24:$C$35,3,FALSE) -> 100000 | E18: =C18*IF(Inputs!$B$4="Stress",Inputs!$B$12,Inputs!$B$11) -> 23400 | F18: =C18*Inputs!$B$13 -> 156000 | G18: =VLOOKUP(F18,Tiers!$A$4:$B$7,2,TRUE)*IF(Inputs!$B$4="Stress",Inputs!$B$14,1) -> 0.6 | H18: =MIN(C18*Inputs!$B$15,F18*G18) -> 70200 | I18: =H18/C18 -> 0.45 | J18: =VLOOKUP($A18,Inputs!$A$24:$D$35,4,FALSE) -> 0 | K18: =IF($Q18>=Inputs!$B$17,Inputs!$B$16,0) -> 0 | L18: =IF($Q18>=Inputs!$B$19,Inputs!$B$18,0) -> 16200 | M18: =SUM(D18,E18,H18,J18,K18,L18) -> 209800 | N18: =C18-M18 -> -53800 | O18: =IF($Q18=Inputs!$B$8,Inputs!$B$7,0) -> 0 | P18: =B18+N18+O18 -> 2018600 | Q18: 11
A19: 46357 | B19: =P18 -> 2018600 | C19: =VLOOKUP($A19,Inputs!$A$24:$B$35,2,FALSE)*IF(Inputs!$B$4="Stress",Inputs!$B$5,1) -> 187000 | D19: =VLOOKUP($A19,Inputs!$A$24:$C$35,3,FALSE) -> 100000 | E19: =C19*IF(Inputs!$B$4="Stress",Inputs!$B$12,Inputs!$B$11) -> 28050 | F19: =C19*Inputs!$B$13 -> 187000 | G19: =VLOOKUP(F19,Tiers!$A$4:$B$7,2,TRUE)*IF(Inputs!$B$4="Stress",Inputs!$B$14,1) -> 0.6 | H19: =MIN(C19*Inputs!$B$15,F19*G19) -> 84150 | I19: =H19/C19 -> 0.45 | J19: =VLOOKUP($A19,Inputs!$A$24:$D$35,4,FALSE) -> 0 | K19: =IF($Q19>=Inputs!$B$17,Inputs!$B$16,0) -> 0 | L19: =IF($Q19>=Inputs!$B$19,Inputs!$B$18,0) -> 16200 | M19: =SUM(D19,E19,H19,J19,K19,L19) -> 228400 | N19: =C19-M19 -> -41400 | O19: =IF($Q19=Inputs!$B$8,Inputs!$B$7,0) -> 0 | P19: =B19+N19+O19 -> 1977200 | Q19: 12
A20: Total / Avg | C20: =SUM(C8:C19) -> 994000 | D20: =SUM(D8:D19) -> 1110000 | E20: =SUM(E8:E19) -> 149100 | G20: =AVERAGE(G8:G19) -> 0.56666667 | H20: =SUM(H8:H19) -> 447300 | J20: =SUM(J8:J19) -> 116000 | K20: =SUM(K8:K19) -> 0 | L20: =SUM(L8:L19) -> 194400 | M20: =SUM(M8:M19) -> 2016800 | N20: =SUM(N8:N19) -> -1022800 | O20: =SUM(O8:O19) -> 2000000 | P20: =P19 -> 1977200

Sheet StressTest
A1: Stress Test (Base vs Revenue Downside)
A3: Downside multiplier: | B3: =Inputs!$B$5 -> 0.75
A4: This sheet calculates Base and Stress in parallel (no scenario toggle needed).
A5: Month | B5: End Cash (Base) | C5: End Cash (Stress) | D5: Net CF (Base) | E5: Net CF (Stress) | F5: Min Cash (Base) | G5: Min Cash (Stress) | H5: Month#
A6: 46023 | B6: =Inputs!$B$6+D6+(IF($H6=Inputs!$B$8,Inputs!$B$7,0)) -> 850800 | C6: =Inputs!$B$6+E6+(IF($H6=Inputs!$B$8,Inputs!$B$7,0)) -> 850925 | D6: =(VLOOKUP($A6,Inputs!$A$24:$B$35,2,FALSE))-(SUM(VLOOKUP($A6,Inputs!$A$24:$C$35,3,FALSE),(VLOOKUP($A6,Inputs!$A$24:$B$35,2,FALSE))*Inputs!$B$11,MIN((VLOOKUP($A6,Inputs!$A$24:$B$35,2,FALSE))*Inputs!$B$15,((VLOOKUP($A6,Inputs!$A$24:$B$35,2,FALSE))*Inputs!$B$13)*(VLOOKUP((VLOOKUP($A6,Inputs!$A$24:$B$35,2,FALSE))*Inputs!$B$13,Tiers!$A$4:$B$7,2,TRUE))),VLOOKUP($A6,Inputs!$A$24:$D$35,4,FALSE),IF($H6>=Inputs!$B$17,Inputs!$B$16,0),IF($H6>=Inputs!$B$19,Inputs!$B$18,0))) -> -149200 | E6: =((VLOOKUP($A6,Inputs!$A$24:$B$35,2,FALSE))*Inputs!$B$5)-(SUM(VLOOKUP($A6,Inputs!$A$24:$C$35,3,FALSE),((VLOOKUP($A6,Inputs!$A$24:$B$35,2,FALSE))*Inputs!$B$5)*Inputs!$B$12,MIN(((VLOOKUP($A6,Inputs!$A$24:$B$35,2,FALSE))*Inputs!$B$5)*Inputs!$B$15,(((VLOOKUP($A6,Inputs!$A$24:$B$35,2,FALSE))*Inputs!$B$5)*Inputs!$B$13)*(VLOOKUP(((VLOOKUP($A6,Inputs!$A$24:$B$35,2,FALSE))*Inputs!$B$5)*Inputs!$B$13,Tiers!$A$4:$B$7,2,TRUE)*Inputs!$B$14)),VLOOKUP($A6,Inputs!$A$24:$D$35,4,FALSE),IF($H6>=Inputs!$B$17,Inputs!$B$16,0),IF($H6>=Inputs!$B$19,Inputs!$B$18,0))) -> -149075 | F6: =MIN(B6:B17) -> 590800 | G6: =MIN(C6:C17) -> 584112.5 | H6: 1
A7: 46054 | B7: =B6+D7+(IF($H7=Inputs!$B$8,Inputs!$B$7,0)) -> 761600 | C7: =C6+E7+(IF($H7=Inputs!$B$8,Inputs!$B$7,0)) -> 759850 | D7: =(VLOOKUP($A7,Inputs!$A$24:$B$35,2,FALSE))-(SUM(VLOOKUP($A7,Inputs!$A$24:$C$35,3,FALSE),(VLOOKUP($A7,Inputs!$A$24:$B$35,2,FALSE))*Inputs!$B$11,MIN((VLOOKUP($A7,Inputs!$A$24:$B$35,2,FALSE))*Inputs!$B$15,((VLOOKUP($A7,Inputs!$A$24:$B$35,2,FALSE))*Inputs!$B$13)*(VLOOKUP((VLOOKUP($A7,Inputs!$A$24:$B$35,2,FALSE))*Inputs!$B$13,Tiers!$A$4:$B$7,2,TRUE))),VLOOKUP($A7,Inputs!$A$24:$D$35,4,FALSE),IF($H7>=Inputs!$B$17,Inputs!$B$16,0),IF($H7>=Inputs!$B$19,Inputs!$B$18,0))) -> -89200 | E7: =((VLOOKUP($A7,Inputs!$A$24:$B$35,2,FALSE))*Inputs!$B$5)-(SUM(VLOOKUP($A7,Inputs!$A$24:$C$35,3,FALSE),((VLOOKUP($A7,Inputs!$A$24:$B$35,2,FALSE))*Inputs!$B$5)*Inputs!$B$12,MIN(((VLOOKUP($A7,Inputs!$A$24:$B$35,2,FALSE))*Inputs!$B$5)*Inputs!$B$15,(((VLOOKUP($A7,Inputs!$A$24:$B$35,2,FALSE))*Inputs!$B$5)*Inputs!$B$13)*(VLOOKUP(((VLOOKUP($A7,Inputs!$A$24:$B$35,2,FALSE))*Inputs!$B$5)*Inputs!$B$13,Tiers!$A$4:$B$7,2,TRUE)*Inputs!$B$14)),VLOOKUP($A7,Inputs!$A$24:$D$35,4,FALSE),IF($H7>=Inputs!$B$17,Inputs!$B$16,0),IF($H7>=Inputs!$B$19,Inputs!$B$18,0))) -> -91075 | H7: 2
A8: 46082 | B8: =B7+D8+(IF($H8=Inputs!$B$8,Inputs!$B$7,0)) -> 674800 | C8: =C7+E8+(IF($H8=Inputs!$B$8,Inputs!$B$7,0)) -> 670800 | D8: =(VLOOKUP($A8,Inputs!$A$24:$B$35,2,FALSE))-(SUM(VLOOKUP($A8,Inputs!$A$24:$C$35,3,FALSE),(VLOOKUP($A8,Inputs!$A$24:$B$35,2,FALSE))*Inputs!$B$11,MIN((VLOOKUP($A8,Inputs!$A$24:$B$35,2,FALSE))*Inputs!$B$15,((VLOOKUP($A8,Inputs!$A$24:$B$35,2,FALSE))*Inputs!$B$13)*(VLOOKUP((VLOOKUP($A8,Inputs!$A$24:$B$35,2,FALSE))*Inputs!$B$13,Tiers!$A$4:$B$7,2,TRUE))),VLOOKUP($A8,Inputs!$A$24:$D$35,4,FALSE),IF($H8>=Inputs!$B$17,Inputs!$B$16,0),IF($H8>=Inputs!$B$19,Inputs!$B$18,0))) -> -86800 | E8: =((VLOOKUP($A8,Inputs!$A$24:$B$35,2,FALSE))*Inputs!$B$5)-(SUM(VLOOKUP($A8,Inputs!$A$24:$C$35,3,FALSE),((VLOOKUP($A8,Inputs!$A$24:$B$35,2,FALSE))*Inputs!$B$5)*Inputs!$B$12,MIN(((VLOOKUP($A8,Inputs!$A$24:$B$35,2,FALSE))*Inputs!$B$5)*Inputs!$B$15,(((VLOOKUP($A8,Inputs!$A$24:$B$35,2,FALSE))*Inputs!$B$5)*Inputs!$B$13)*(VLOOKUP(((VLOOKUP($A8,Inputs!$A$24:$B$35,2,FALSE))*Inputs!$B$5)*Inputs!$B$13,Tiers!$A$4:$B$7,2,TRUE)*Inputs!$B$14)),VLOOKUP($A8,Inputs!$A$24:$D$35,4,FALSE),IF($H8>=Inputs!$B$17,Inputs!$B$16,0),IF($H8>=Inputs!$B$19,Inputs!$B$18,0))) -> -89050 | H8: 3
A9: 46113 | B9: =B8+D9+(IF($H9=Inputs!$B$8,Inputs!$B$7,0)) -> 590800 | C9: =C8+E9+(IF($H9=Inputs!$B$8,Inputs!$B$7,0)) -> 584112.5 | D9: =(VLOOKUP($A9,Inputs!$A$24:$B$35,2,FALSE))-(SUM(VLOOKUP($A9,Inputs!$A$24:$C$35,3,FALSE),(VLOOKUP($A9,Inputs!$A$24:$B$35,2,FALSE))*Inputs!$B$11,MIN((VLOOKUP($A9,Inputs!$A$24:$B$35,2,FALSE))*Inputs!$B$15,((VLOOKUP($A9,Inputs!$A$24:$B$35,2,FALSE))*Inputs!$B$13)*(VLOOKUP((VLOOKUP($A9,Inputs!$A$24:$B$35,2,FALSE))*Inputs!$B$13,Tiers!$A$4:$B$7,2,TRUE))),VLOOKUP($A9,Inputs!$A$24:$D$35,4,FALSE),IF($H9>=Inputs!$B$17,Inputs!$B$16,0),IF($H9>=Inputs!$B$19,Inputs!$B$18,0))) -> -84000 | E9: =((VLOOKUP($A9,Inputs!$A$24:$B$35,2,FALSE))*Inputs!$B$5)-(SUM(VLOOKUP($A9,Inputs!$A$24:$C$35,3,FALSE),((VLOOKUP($A9,Inputs!$A$24:$B$35,2,FALSE))*Inputs!$B$5)*Inputs!$B$12,MIN(((VLOOKUP($A9,Inputs!$A$24:$B$35,2,FALSE))*Inputs!$B$5)*Inputs!$B$15,(((VLOOKUP($A9,Inputs!$A$24:$B$35,2,FALSE))*Inputs!$B$5)*Inputs!$B$13)*(VLOOKUP(((VLOOKUP($A9,Inputs!$A$24:$B$35,2,FALSE))*Inputs!$B$5)*Inputs!$B$13,Tiers!$A$4:$B$7,2,TRUE)*Inputs!$B$14)),VLOOKUP($A9,Inputs!$A$24:$D$35,4,FALSE),IF($H9>=Inputs!$B$17,Inputs!$B$16,0),IF($H9>=Inputs!$B$19,Inputs!$B$18,0))) -> -86687.5 | H9: 4
A10: 46143 | B10: =B9+D10+(IF($H10=Inputs!$B$8,Inputs!$B$7,0)) -> 2510400 | C10: =C9+E10+(IF($H10=Inputs!$B$8,Inputs!$B$7,0)) -> 2500462.5 | D10: =(VLOOKUP($A10,Inputs!$A$24:$B$35,2,FALSE))-(SUM(VLOOKUP($A10,Inputs!$A$24:$C$35,3,FALSE),(VLOOKUP($A10,Inputs!$A$24:$B$35,2,FALSE))*Inputs!$B$11,MIN((VLOOKUP($A10,Inputs!$A$24:$B$35,2,FALSE))*Inputs!$B$15,((VLOOKUP($A10,Inputs!$A$24:$B$35,2,FALSE))*Inputs!$B$13)*(VLOOKUP((VLOOKUP($A10,Inputs!$A$24:$B$35,2,FALSE))*Inputs!$B$13,Tiers!$A$4:$B$7,2,TRUE))),VLOOKUP($A10,Inputs!$A$24:$D$35,4,FALSE),IF($H10>=Inputs!$B$17,Inputs!$B$16,0),IF($H10>=Inputs!$B$19,Inputs!$B$18,0))) -> -80400 | E10: =((VLOOKUP($A10,Inputs!$A$24:$B$35,2,FALSE))*Inputs!$B$5)-(SUM(VLOOKUP($A10,Inputs!$A$24:$C$35,3,FALSE),((VLOOKUP($A10,Inputs!$A$24:$B$35,2,FALSE))*Inputs!$B$5)*Inputs!$B$12,MIN(((VLOOKUP($A10,Inputs!$A$24:$B$35,2,FALSE))*Inputs!$B$5)*Inputs!$B$15,(((VLOOKUP($A10,Inputs!$A$24:$B$35,2,FALSE))*Inputs!$B$5)*Inputs!$B$13)*(VLOOKUP(((VLOOKUP($A10,Inputs!$A$24:$B$35,2,FALSE))*Inputs!$B$5)*Inputs!$B$13,Tiers!$A$4:$B$7,2,TRUE)*Inputs!$B$14)),VLOOKUP($A10,Inputs!$A$24:$D$35,4,FALSE),IF($H10>=Inputs!$B$17,Inputs!$B$16,0),IF($H10>=Inputs!$B$19,Inputs!$B$18,0))) -> -83650 | H10: 5
A11: 46174 | B11: =B10+D11+(IF($H11=Inputs!$B$8,Inputs!$B$7,0)) -> 2434000 | C11: =C10+E11+(IF($H11=Inputs!$B$8,Inputs!$B$7,0)) -> 2420187.5 | D11: =(VLOOKUP($A11,Inputs!$A$24:$B$35,2,FALSE))-(SUM(VLOOKUP($A11,Inputs!$A$24:$C$35,3,FALSE),(VLOOKUP($A11,Inputs!$A$24:$B$35,2,FALSE))*Inputs!$B$11,MIN((VLOOKUP($A11,Inputs!$A$24:$B$35,2,FALSE))*Inputs!$B$15,((VLOOKUP($A11,Inputs!$A$24:$B$35,2,FALSE))*Inputs!$B$13)*(VLOOKUP((VLOOKUP($A11,Inputs!$A$24:$B$35,2,FALSE))*Inputs!$B$13,Tiers!$A$4:$B$7,2,TRUE))),VLOOKUP($A11,Inputs!$A$24:$D$35,4,FALSE),IF($H11>=Inputs!$B$17,Inputs!$B$16,0),IF($H11>=Inputs!$B$19,Inputs!$B$18,0))) -> -76400 | E11: =((VLOOKUP($A11,Inputs!$A$24:$B$35,2,FALSE))*Inputs!$B$5)-(SUM(VLOOKUP($A11,Inputs!$A$24:$C$35,3,FALSE),((VLOOKUP($A11,Inputs!$A$24:$B$35,2,FALSE))*Inputs!$B$5)*Inputs!$B$12,MIN(((VLOOKUP($A11,Inputs!$A$24:$B$35,2,FALSE))*Inputs!$B$5)*Inputs!$B$15,(((VLOOKUP($A11,Inputs!$A$24:$B$35,2,FALSE))*Inputs!$B$5)*Inputs!$B$13)*(VLOOKUP(((VLOOKUP($A11,Inputs!$A$24:$B$35,2,FALSE))*Inputs!$B$5)*Inputs!$B$13,Tiers!$A$4:$B$7,2,TRUE)*Inputs!$B$14)),VLOOKUP($A11,Inputs!$A$24:$D$35,4,FALSE),IF($H11>=Inputs!$B$17,Inputs!$B$16,0),IF($H11>=Inputs!$B$19,Inputs!$B$18,0))) -> -80275 | H11: 6
A12: 46204 | B12: =B11+D12+(IF($H12=Inputs!$B$8,Inputs!$B$7,0)) -> 2289800 | C12: =C11+E12+(IF($H12=Inputs!$B$8,Inputs!$B$7,0)) -> 2271300 | D12: =(VLOOKUP($A12,Inputs!$A$24:$B$35,2,FALSE))-(SUM(VLOOKUP($A12,Inputs!$A$24:$C$35,3,FALSE),(VLOOKUP($A12,Inputs!$A$24:$B$35,2,FALSE))*Inputs!$B$11,MIN((VLOOKUP($A12,Inputs!$A$24:$B$35,2,FALSE))*Inputs!$B$15,((VLOOKUP($A12,Inputs!$A$24:$B$35,2,FALSE))*Inputs!$B$13)*(VLOOKUP((VLOOKUP($A12,Inputs!$A$24:$B$35,2,FALSE))*Inputs!$B$13,Tiers!$A$4:$B$7,2,TRUE))),VLOOKUP($A12,Inputs!$A$24:$D$35,4,FALSE),IF($H12>=Inputs!$B$17,Inputs!$B$16,0),IF($H12>=Inputs!$B$19,Inputs!$B$18,0))) -> -144200 | E12: =((VLOOKUP($A12,Inputs!$A$24:$B$35,2,FALSE))*Inputs!$B$5)-(SUM(VLOOKUP($A12,Inputs!$A$24:$C$35,3,FALSE),((VLOOKUP($A12,Inputs!$A$24:$B$35,2,FALSE))*Inputs!$B$5)*Inputs!$B$12,MIN(((VLOOKUP($A12,Inputs!$A$24:$B$35,2,FALSE))*Inputs!$B$5)*Inputs!$B$15,(((VLOOKUP($A12,Inputs!$A$24:$B$35,2,FALSE))*Inputs!$B$5)*Inputs!$B$13)*(VLOOKUP(((VLOOKUP($A12,Inputs!$A$24:$B$35,2,FALSE))*Inputs!$B$5)*Inputs!$B$13,Tiers!$A$4:$B$7,2,TRUE)*Inputs!$B$14)),VLOOKUP($A12,Inputs!$A$24:$D$35,4,FALSE),IF($H12>=Inputs!$B$17,Inputs!$B$16,0),IF($H12>=Inputs!$B$19,Inputs!$B$18,0))) -> -148887.5 | H12: 7
A13: 46235 | B13: =B12+D13+(IF($H13=Inputs!$B$8,Inputs!$B$7,0)) -> 2209600 | C13: =C12+E13+(IF($H13=Inputs!$B$8,Inputs!$B$7,0)) -> 2185475 | D13: =(VLOOKUP($A13,Inputs!$A$24:$B$35,2,FALSE))-(SUM(VLOOKUP($A13,Inputs!$A$24:$C$35,3,FALSE),(VLOOKUP($A13,Inputs!$A$24:$B$35,2,FALSE))*Inputs!$B$11,MIN((VLOOKUP($A13,Inputs!$A$24:$B$35,2,FALSE))*Inputs!$B$15,((VLOOKUP($A13,Inputs!$A$24:$B$35,2,FALSE))*Inputs!$B$13)*(VLOOKUP((VLOOKUP($A13,Inputs!$A$24:$B$35,2,FALSE))*Inputs!$B$13,Tiers!$A$4:$B$7,2,TRUE))),VLOOKUP($A13,Inputs!$A$24:$D$35,4,FALSE),IF($H13>=Inputs!$B$17,Inputs!$B$16,0),IF($H13>=Inputs!$B$19,Inputs!$B$18,0))) -> -80200 | E13: =((VLOOKUP($A13,Inputs!$A$24:$B$35,2,FALSE))*Inputs!$B$5)-(SUM(VLOOKUP($A13,Inputs!$A$24:$C$35,3,FALSE),((VLOOKUP($A13,Inputs!$A$24:$B$35,2,FALSE))*Inputs!$B$5)*Inputs!$B$12,MIN(((VLOOKUP($A13,Inputs!$A$24:$B$35,2,FALSE))*Inputs!$B$5)*Inputs!$B$15,(((VLOOKUP($A13,Inputs!$A$24:$B$35,2,FALSE))*Inputs!$B$5)*Inputs!$B$13)*(VLOOKUP(((VLOOKUP($A13,Inputs!$A$24:$B$35,2,FALSE))*Inputs!$B$5)*Inputs!$B$13,Tiers!$A$4:$B$7,2,TRUE)*Inputs!$B$14)),VLOOKUP($A13,Inputs!$A$24:$D$35,4,FALSE),IF($H13>=Inputs!$B$17,Inputs!$B$16,0),IF($H13>=Inputs!$B$19,Inputs!$B$18,0))) -> -85825 | H13: 8
A14: 46266 | B14: =B13+D14+(IF($H14=Inputs!$B$8,Inputs!$B$7,0)) -> 2136600 | C14: =C13+E14+(IF($H14=Inputs!$B$8,Inputs!$B$7,0)) -> 2105725 | D14: =(VLOOKUP($A14,Inputs!$A$24:$B$35,2,FALSE))-(SUM(VLOOKUP($A14,Inputs!$A$24:$C$35,3,FALSE),(VLOOKUP($A14,Inputs!$A$24:$B$35,2,FALSE))*Inputs!$B$11,MIN((VLOOKUP($A14,Inputs!$A$24:$B$35,2,FALSE))*Inputs!$B$15,((VLOOKUP($A14,Inputs!$A$24:$B$35,2,FALSE))*Inputs!$B$13)*(VLOOKUP((VLOOKUP($A14,Inputs!$A$24:$B$35,2,FALSE))*Inputs!$B$13,Tiers!$A$4:$B$7,2,TRUE))),VLOOKUP($A14,Inputs!$A$24:$D$35,4,FALSE),IF($H14>=Inputs!$B$17,Inputs!$B$16,0),IF($H14>=Inputs!$B$19,Inputs!$B$18,0))) -> -73000 | E14: =((VLOOKUP($A14,Inputs!$A$24:$B$35,2,FALSE))*Inputs!$B$5)-(SUM(VLOOKUP($A14,Inputs!$A$24:$C$35,3,FALSE),((VLOOKUP($A14,Inputs!$A$24:$B$35,2,FALSE))*Inputs!$B$5)*Inputs!$B$12,MIN(((VLOOKUP($A14,Inputs!$A$24:$B$35,2,FALSE))*Inputs!$B$5)*Inputs!$B$15,(((VLOOKUP($A14,Inputs!$A$24:$B$35,2,FALSE))*Inputs!$B$5)*Inputs!$B$13)*(VLOOKUP(((VLOOKUP($A14,Inputs!$A$24:$B$35,2,FALSE))*Inputs!$B$5)*Inputs!$B$13,Tiers!$A$4:$B$7,2,TRUE)*Inputs!$B$14)),VLOOKUP($A14,Inputs!$A$24:$D$35,4,FALSE),IF($H14>=Inputs!$B$17,Inputs!$B$16,0),IF($H14>=Inputs!$B$19,Inputs!$B$18,0))) -> -79750 | H14: 9
A15: 46296 | B15: =B14+D15+(IF($H15=Inputs!$B$8,Inputs!$B$7,0)) -> 2072400 | C15: =C14+E15+(IF($H15=Inputs!$B$8,Inputs!$B$7,0)) -> 2033400 | D15: =(VLOOKUP($A15,Inputs!$A$24:$B$35,2,FALSE))-(SUM(VLOOKUP($A15,Inputs!$A$24:$C$35,3,FALSE),(VLOOKUP($A15,Inputs!$A$24:$B$35,2,FALSE))*Inputs!$B$11,MIN((VLOOKUP($A15,Inputs!$A$24:$B$35,2,FALSE))*Inputs!$B$15,((VLOOKUP($A15,Inputs!$A$24:$B$35,2,FALSE))*Inputs!$B$13)*(VLOOKUP((VLOOKUP($A15,Inputs!$A$24:$B$35,2,FALSE))*Inputs!$B$13,Tiers!$A$4:$B$7,2,TRUE))),VLOOKUP($A15,Inputs!$A$24:$D$35,4,FALSE),IF($H15>=Inputs!$B$17,Inputs!$B$16,0),IF($H15>=Inputs!$B$19,Inputs!$B$18,0))) -> -64200 | E15: =((VLOOKUP($A15,Inputs!$A$24:$B$35,2,FALSE))*Inputs!$B$5)-(SUM(VLOOKUP($A15,Inputs!$A$24:$C$35,3,FALSE),((VLOOKUP($A15,Inputs!$A$24:$B$35,2,FALSE))*Inputs!$B$5)*Inputs!$B$12,MIN(((VLOOKUP($A15,Inputs!$A$24:$B$35,2,FALSE))*Inputs!$B$5)*Inputs!$B$15,(((VLOOKUP($A15,Inputs!$A$24:$B$35,2,FALSE))*Inputs!$B$5)*Inputs!$B$13)*(VLOOKUP(((VLOOKUP($A15,Inputs!$A$24:$B$35,2,FALSE))*Inputs!$B$5)*Inputs!$B$13,Tiers!$A$4:$B$7,2,TRUE)*Inputs!$B$14)),VLOOKUP($A15,Inputs!$A$24:$D$35,4,FALSE),IF($H15>=Inputs!$B$17,Inputs!$B$16,0),IF($H15>=Inputs!$B$19,Inputs!$B$18,0))) -> -72325 | H15: 10
A16: 46327 | B16: =B15+D16+(IF($H16=Inputs!$B$8,Inputs!$B$7,0)) -> 2018600 | C16: =C15+E16+(IF($H16=Inputs!$B$8,Inputs!$B$7,0)) -> 1969850 | D16: =(VLOOKUP($A16,Inputs!$A$24:$B$35,2,FALSE))-(SUM(VLOOKUP($A16,Inputs!$A$24:$C$35,3,FALSE),(VLOOKUP($A16,Inputs!$A$24:$B$35,2,FALSE))*Inputs!$B$11,MIN((VLOOKUP($A16,Inputs!$A$24:$B$35,2,FALSE))*Inputs!$B$15,((VLOOKUP($A16,Inputs!$A$24:$B$35,2,FALSE))*Inputs!$B$13)*(VLOOKUP((VLOOKUP($A16,Inputs!$A$24:$B$35,2,FALSE))*Inputs!$B$13,Tiers!$A$4:$B$7,2,TRUE))),VLOOKUP($A16,Inputs!$A$24:$D$35,4,FALSE),IF($H16>=Inputs!$B$17,Inputs!$B$16,0),IF($H16>=Inputs!$B$19,Inputs!$B$18,0))) -> -53800 | E16: =((VLOOKUP($A16,Inputs!$A$24:$B$35,2,FALSE))*Inputs!$B$5)-(SUM(VLOOKUP($A16,Inputs!$A$24:$C$35,3,FALSE),((VLOOKUP($A16,Inputs!$A$24:$B$35,2,FALSE))*Inputs!$B$5)*Inputs!$B$12,MIN(((VLOOKUP($A16,Inputs!$A$24:$B$35,2,FALSE))*Inputs!$B$5)*Inputs!$B$15,(((VLOOKUP($A16,Inputs!$A$24:$B$35,2,FALSE))*Inputs!$B$5)*Inputs!$B$13)*(VLOOKUP(((VLOOKUP($A16,Inputs!$A$24:$B$35,2,FALSE))*Inputs!$B$5)*Inputs!$B$13,Tiers!$A$4:$B$7,2,TRUE)*Inputs!$B$14)),VLOOKUP($A16,Inputs!$A$24:$D$35,4,FALSE),IF($H16>=Inputs!$B$17,Inputs!$B$16,0),IF($H16>=Inputs!$B$19,Inputs!$B$18,0))) -> -63550 | H16: 11
A17: 46357 | B17: =B16+D17+(IF($H17=Inputs!$B$8,Inputs!$B$7,0)) -> 1977200 | C17: =C16+E17+(IF($H17=Inputs!$B$8,Inputs!$B$7,0)) -> 1916762.5 | D17: =(VLOOKUP($A17,Inputs!$A$24:$B$35,2,FALSE))-(SUM(VLOOKUP($A17,Inputs!$A$24:$C$35,3,FALSE),(VLOOKUP($A17,Inputs!$A$24:$B$35,2,FALSE))*Inputs!$B$11,MIN((VLOOKUP($A17,Inputs!$A$24:$B$35,2,FALSE))*Inputs!$B$15,((VLOOKUP($A17,Inputs!$A$24:$B$35,2,FALSE))*Inputs!$B$13)*(VLOOKUP((VLOOKUP($A17,Inputs!$A$24:$B$35,2,FALSE))*Inputs!$B$13,Tiers!$A$4:$B$7,2,TRUE))),VLOOKUP($A17,Inputs!$A$24:$D$35,4,FALSE),IF($H17>=Inputs!$B$17,Inputs!$B$16,0),IF($H17>=Inputs!$B$19,Inputs!$B$18,0))) -> -41400 | E17: =((VLOOKUP($A17,Inputs!$A$24:$B$35,2,FALSE))*Inputs!$B$5)-(SUM(VLOOKUP($A17,Inputs!$A$24:$C$35,3,FALSE),((VLOOKUP($A17,Inputs!$A$24:$B$35,2,FALSE))*Inputs!$B$5)*Inputs!$B$12,MIN(((VLOOKUP($A17,Inputs!$A$24:$B$35,2,FALSE))*Inputs!$B$5)*Inputs!$B$15,(((VLOOKUP($A17,Inputs!$A$24:$B$35,2,FALSE))*Inputs!$B$5)*Inputs!$B$13)*(VLOOKUP(((VLOOKUP($A17,Inputs!$A$24:$B$35,2,FALSE))*Inputs!$B$5)*Inputs!$B$13,Tiers!$A$4:$B$7,2,TRUE)*Inputs!$B$14)),VLOOKUP($A17,Inputs!$A$24:$D$35,4,FALSE),IF($H17>=Inputs!$B$17,Inputs!$B$16,0),IF($H17>=Inputs!$B$19,Inputs!$B$18,0))) -> -53087.5 | H17: 12
A19: Interpretation: If 'Min Cash (Stress)' drops below your 3-month fixed-cost buffer, activate cost controls.
